{
  "Author": "mowori",
  "Name": "Distant Seas (but with spectral time)",
  "Punchline": "The ultimate Ocean Fishing plugin.",
  "Description": "The ultimate Ocean Fishing plugin. Automatically suggests baits, logs each boat you're on, tracks progress to achievements, adds a global point leaderboard, and more!\n\nIcon from the Mutant Standard project.",
  "InternalName": "DistantSeas",
  "IconUrl": "https://raw.githubusercontent.com/mowori/DistantSeas/main/Data/icon.png",
  "RepoUrl": "https://github.com/mowori/DistantSeas",
  "ApplicableVersion": "any",
  "Tags": [
    "ocean",
    "fishing"
  ]
}
